uw_restclients_uwnetid-1.1.4.dist-info/licenses/LICENSE
uw_uwnetid/VERSION
uw_uwnetid/__init__.py
uw_uwnetid/admin.py
uw_uwnetid/category.py
uw_uwnetid/dao.py
uw_uwnetid/models.py
uw_uwnetid/password.py
uw_uwnetid/subscription.py
uw_uwnetid/subscription_105.py
uw_uwnetid/subscription_233.py
uw_uwnetid/subscription_60.py
uw_uwnetid/subscription_64.py
uw_uwnetid/supported.py
uw_uwnetid/test.py
uw_uwnetid/util.py
uw_uwnetid/resources/uwnetid/file/nws/v1/category.POST
uw_uwnetid/resources/uwnetid/file/nws/v1/subscription.json.POST
uw_uwnetid/resources/uwnetid/file/nws/v1/uwnetid/bill/password
uw_uwnetid/resources/uwnetid/file/nws/v1/uwnetid/bill/supported.json
uw_uwnetid/resources/uwnetid/file/nws/v1/uwnetid/bill/subscription/233
uw_uwnetid/resources/uwnetid/file/nws/v1/uwnetid/bill/subscription/234
uw_uwnetid/resources/uwnetid/file/nws/v1/uwnetid/bill/subscription/60
uw_uwnetid/resources/uwnetid/file/nws/v1/uwnetid/bill/subscription/64
uw_uwnetid/resources/uwnetid/file/nws/v1/uwnetid/eight/password
uw_uwnetid/resources/uwnetid/file/nws/v1/uwnetid/eight/subscription/105
uw_uwnetid/resources/uwnetid/file/nws/v1/uwnetid/eight/subscription/60
uw_uwnetid/resources/uwnetid/file/nws/v1/uwnetid/emailinfo/admin.json
uw_uwnetid/resources/uwnetid/file/nws/v1/uwnetid/fred/subscription/60
uw_uwnetid/resources/uwnetid/file/nws/v1/uwnetid/invalidnetid/subscription/105
uw_uwnetid/resources/uwnetid/file/nws/v1/uwnetid/james/subscription/60
uw_uwnetid/resources/uwnetid/file/nws/v1/uwnetid/javerage/password
uw_uwnetid/resources/uwnetid/file/nws/v1/uwnetid/javerage/category/25
uw_uwnetid/resources/uwnetid/file/nws/v1/uwnetid/javerage/category/index.html
uw_uwnetid/resources/uwnetid/file/nws/v1/uwnetid/javerage/subscription/105
uw_uwnetid/resources/uwnetid/file/nws/v1/uwnetid/javerage/subscription/233.POST
uw_uwnetid/resources/uwnetid/file/nws/v1/uwnetid/javerage/subscription/60
"uw_uwnetid/resources/uwnetid/file/nws/v1/uwnetid/javerage/subscription/60,20,100,105,137,41"
uw_uwnetid/resources/uwnetid/file/nws/v1/uwnetid/javerage/subscription/64
uw_restclients_uwnetid-1.1.4.dist-info/METADATA
uw_restclients_uwnetid-1.1.4.dist-info/WHEEL
uw_restclients_uwnetid-1.1.4.dist-info/top_level.txt
uw_restclients_uwnetid-1.1.4.dist-info/RECORD
